PyKMIP-0.8.0.dist-info/DESCRIPTION.rst
PyKMIP-0.8.0.dist-info/METADATA
PyKMIP-0.8.0.dist-info/RECORD
PyKMIP-0.8.0.dist-info/WHEEL
PyKMIP-0.8.0.dist-info/entry_points.txt
PyKMIP-0.8.0.dist-info/metadata.json
PyKMIP-0.8.0.dist-info/top_level.txt
kmip/__init__.py
kmip/version.py
kmip/core/__init__.py
kmip/core/attributes.py
kmip/core/config_helper.py
kmip/core/enums.py
kmip/core/exceptions.py
kmip/core/misc.py
kmip/core/objects.py
kmip/core/policy.py
kmip/core/primitives.py
kmip/core/secrets.py
kmip/core/utils.py
kmip/core/factories/__init__.py
kmip/core/factories/attribute_values.py
kmip/core/factories/attributes.py
kmip/core/factories/credentials.py
kmip/core/factories/secrets.py
kmip/core/factories/payloads/__init__.py
kmip/core/factories/payloads/request.py
kmip/core/factories/payloads/response.py
kmip/core/messages/__init__.py
kmip/core/messages/contents.py
kmip/core/messages/messages.py
kmip/core/messages/payloads/__init__.py
kmip/core/messages/payloads/activate.py
kmip/core/messages/payloads/archive.py
kmip/core/messages/payloads/cancel.py
kmip/core/messages/payloads/check.py
kmip/core/messages/payloads/create.py
kmip/core/messages/payloads/create_key_pair.py
kmip/core/messages/payloads/decrypt.py
kmip/core/messages/payloads/derive_key.py
kmip/core/messages/payloads/destroy.py
kmip/core/messages/payloads/discover_versions.py
kmip/core/messages/payloads/encrypt.py
kmip/core/messages/payloads/get.py
kmip/core/messages/payloads/get_attribute_list.py
kmip/core/messages/payloads/get_attributes.py
kmip/core/messages/payloads/get_usage_allocation.py
kmip/core/messages/payloads/locate.py
kmip/core/messages/payloads/mac.py
kmip/core/messages/payloads/obtain_lease.py
kmip/core/messages/payloads/poll.py
kmip/core/messages/payloads/query.py
kmip/core/messages/payloads/recover.py
kmip/core/messages/payloads/register.py
kmip/core/messages/payloads/rekey.py
kmip/core/messages/payloads/rekey_key_pair.py
kmip/core/messages/payloads/revoke.py
kmip/core/messages/payloads/sign.py
kmip/core/messages/payloads/signature_verify.py
kmip/demos/__init__.py
kmip/demos/utils.py
kmip/demos/certs/server.crt
kmip/demos/certs/server.key
kmip/demos/pie/__init__.py
