Metadata-Version: 2.0
Name: PyKMIP
Version: 0.8.0
Summary: KMIP v1.1 library
Home-page: https://github.com/OpenKMIP/PyKMIP
Author: Peter Hamilton
Author-email: peter.hamilton@jhuapl.edu
License: Apache License, Version 2.0
Keywords: KMIP
Platform: UNKNOWN
Classifier: Intended Audience :: Developers
Classifier: License :: OSI Approved :: Apache Software License
Classifier: Natural Language :: English
Classifier: Operating System :: POSIX
Classifier: Operating System :: POSIX :: BSD
Classifier: Operating System :: POSIX :: Linux
Classifier: Programming Language :: Python
Classifier: Programming Language :: Python :: 2
Classifier: Programming Language :: Python :: 2.7
Classifier: Programming Language :: Python :: 3.4
Classifier: Programming Language :: Python :: 3.5
Classifier: Programming Language :: Python :: 3.6
Requires-Dist: cryptography
Requires-Dist: enum34
Requires-Dist: six
Requires-Dist: sqlalchemy
